{
  "title": "Siamese Neural Network for User Authentication in Field-Programmable Gate Arrays (FPGAs) for Wearable Applications",
  "year": 2023,
  "venue": "Electronics",
  "doi": "10.3390/electronics12194030",
  "relevance": "include",
  "exclusion_reason": "",
  "rq_category": [
    "RQ1"
  ],
  "biometric": {
    "type": "physiological",
    "modality": [
      "electromyogram (EMG)"
    ],
    "sensor": [
      "Biopac MP160 instrument"
    ],
    "device": [
      "FPGA",
      "wearable device"
    ],
    "body_location": "right arm (palmaris longus and extensor digitorum)"
  },
  "data": [
    {
      "dataset_name": "Chosun University’s dataset",
      "dataset_type": "private",
      "dataset_role": "combined",
      "num_subjects": 100,
      "num_samples": null,
      "collection_setting": "lab",
      "duration": {
        "value": 4,
        "unit": "seconds"
      }
    }
  ],
  "method": {
    "learning_type": "few-shot",
    "model": [
      "Siamese Neural Network",
      "1D-Convolutional Neural Network"
    ],
    "input_representation": "Maximal Overlap Discrete Wavelet Transform (MODWT)",
    "training_strategy": "Keras framework, Adam optimizer, Step decay learning rate, Bit quantization for hardware deployment"
  },
  "evaluation": [
    {
      "metric": "AUC",
      "value": 0.99,
      "context": "Achieved on the training dataset of 80 individuals and maintained during hardware deployment"
    }
  ],
  "evaluation_protocol": "80 subjects for training (with 25% validation) and 20 subjects for testing; binary classification (same person vs different person).",
  "real_world_tested": false,
  "real_world_gap": {
    "environments_compared": false,
    "gap_acknowledged_in_text": true,
    "lab_performance_value": 0.94,
    "real_world_performance_value": null,
    "drop_percentage": null
  },
  "temporal_robustness": {
    "cross_session_tested": false,
    "cross_day_tested": false,
    "longitudinal_duration": {
      "value": null,
      "unit": ""
    },
    "performance_decay_over_time": {
      "is_quantified": false,
      "time_delta": {
        "value": null,
        "unit": ""
      },
      "drop_in_performance": {
        "metric": "",
        "value": null
      }
    }
  },
  "performance_analysis": {
    "robust_to_motion": {
      "is_quantified": false,
      "metric": "",
      "value": null
    },
    "robust_to_noise": {
      "is_quantified": false,
      "metric": "",
      "value": null
    },
    "reported_limitations": [
      "Relatively low accuracy of EMG signals",
      "Limited hardware resources on edge devices",
      "Requirement for multimodal biosignals to further increase accuracy"
    ]
  },
  "security": {
    "spoofing_tested": false,
    "attack_types": [
      "zero-effort"
    ],
    "liveness_detection": false,
    "defense_type": "none"
  },
  "usability": {
    "authentication_type": "implicit",
    "user_interaction_required": true,
    "latency": [
      {
        "value": 1.5,
        "unit": "ms"
      }
    ],
    "energy_consumption": [],
    "usability_study": [],
    "usability_issues": ""
  },
  "fusion": {
    "is_multimodal": false,
    "modalities_combined": [],
    "fusion_level": null,
    "benefit_over_unimodal": []
  },
  "reproducibility": {
    "code_available": false,
    "datasets_all_public": false,
    "datasets_any_public": false,
    "benchmark_used": "Chosun University’s dataset",
    "reproducibility_score": "low"
  },
  "insights": {
    "key_contribution": [
      "Hardware implementation of a lightweight Siamese network on FPGA for EMG authentication",
      "Integration of MODWT for efficient time-frequency feature extraction on edge devices"
    ],
    "main_strength": [
      "Extremely low inference latency (1.5ms)",
      "Few-shot learning capability allowing new users without full retraining",
      "High hardware efficiency with only 6835 parameters"
    ],
    "main_weakness": [
      "Tested on a single specific motion (fist clenching)",
      "Lack of evaluation in uncontrolled/real-world environments",
      "Absence of active spoofing attack tests"
    ],
    "gap_category": [
      "REAL_WORLD_MISSING",
      "NO_SPOOFING_TEST",
      "SINGLE_DATASET_ONLY"
    ],
    "notes_for_review": "The paper focuses heavily on the hardware optimization (FPGA/HLS) rather than the biometric robustness across different activities."
  },
  "extraction_confidence": "high"
}